grex-1.0.2.dist-info/METADATA
grex-1.0.2.dist-info/WHEEL
grex-1.0.2.dist-info/licenses/LICENSE
grex.libs/libgcc_s-98a1ef30.so.1
grex/__init__.py
grex/__init__.pyi
grex/grex.cpython-312-x86_64-linux-musl.so
grex/py.typed
grex-1.0.2.dist-info/RECORD
