Metadata-Version: 2.4
Name: grex
Version: 1.0.2
Classifier: Development Status :: 5 - Production/Stable
Classifier: Intended Audience :: Developers
Classifier: Intended Audience :: Information Technology
Classifier: Intended Audience :: Science/Research
Classifier: License :: OSI Approved :: Apache Software License
Classifier: Programming Language :: Python :: 3.12
Classifier: Programming Language :: Python :: 3.13
Classifier: Programming Language :: Python :: 3.14
Classifier: Programming Language :: Rust
Classifier: Topic :: Software Development :: Libraries :: Python Modules
Classifier: Topic :: Text Processing
Requires-Dist: pytest==9.0.1 ; extra == 'test'
Provides-Extra: test
License-File: LICENSE
Summary: grex generates regular expressions from user-provided test cases.
Keywords: pattern,regex,regexp
Home-Page: https://github.com/pemistahl/grex
Author-email: "Peter M. Stahl" <pemistahl@gmail.com>
Requires-Python: >=3.12
Project-URL: homepage, https://github.com/pemistahl/grex
Project-URL: repository, https://github.com/pemistahl/grex
